firelog/__init__.py
firelog/_event.py
firelog/_ping.py
firelog-0.1.0.dist-info/METADATA
firelog-0.1.0.dist-info/WHEEL
firelog-0.1.0.dist-info/top_level.txt
firelog-0.1.0.dist-info/RECORD
