Metadata-Version: 2.1
Name: firelog
Version: 0.1.0
Summary: FireLog is a simple event logging system based on the firebase database.
Home-page: https://github.com/cansik/firelog
Author: Florian Bruggisser
Author-email: github@broox.ch
License: MIT License
Platform: UNKNOWN
Requires-Dist: requests (>=2.27.1)
